setenvironment/.DS_Store
setenvironment/__init__.py
setenvironment/bash_parser.py
setenvironment/cli.py
setenvironment/main.py
setenvironment/os_env.py
setenvironment/os_env_json.py
setenvironment/setenv.py
setenvironment/setenv_unix.py
setenvironment/setenv_win32.py
setenvironment/types.py
setenvironment/util.py
setenvironment/testing/__init__.py
setenvironment/testing/basetest.py
setenvironment/win/RefreshEnv.cmd
setenvironment/win/__init__.py
setenvironment/win/refresh_env.py
setenvironment/win/registry.py
setenvironment-2.0.3.dist-info/LICENSE
setenvironment-2.0.3.dist-info/METADATA
setenvironment-2.0.3.dist-info/WHEEL
setenvironment-2.0.3.dist-info/entry_points.txt
setenvironment-2.0.3.dist-info/top_level.txt
setenvironment-2.0.3.dist-info/RECORD
