Metadata-Version: 2.1
Name: setenvironment
Version: 2.0.3
Summary: Cross platform(ish) productivity commands written in python.
Home-page: https://github.com/zackees/setenvironment
License: BSD 3-Clause License
Keywords: setenvironment
Classifier: Programming Language :: Python :: 3
Requires-Python: >=3.7
License-File: LICENSE
Requires-Dist: pywin32 ; sys_platform == "win32"
